odoo/addons/crm_won_reason/README.rst
odoo/addons/crm_won_reason/__init__.py
odoo/addons/crm_won_reason/__manifest__.py
odoo/addons/crm_won_reason/i18n/crm_won_reason.pot
odoo/addons/crm_won_reason/i18n/es.po
odoo/addons/crm_won_reason/i18n/it.po
odoo/addons/crm_won_reason/models/__init__.py
odoo/addons/crm_won_reason/models/crm_lead.py
odoo/addons/crm_won_reason/models/crm_lost_reason.py
odoo/addons/crm_won_reason/readme/CONTRIBUTORS.rst
odoo/addons/crm_won_reason/readme/DESCRIPTION.rst
odoo/addons/crm_won_reason/security/ir.model.access.csv
odoo/addons/crm_won_reason/static/description/icon.png
odoo/addons/crm_won_reason/static/description/index.html
odoo/addons/crm_won_reason/tests/__init__.py
odoo/addons/crm_won_reason/tests/test_crm_lead_reason.py
odoo/addons/crm_won_reason/views/crm_views.xml
odoo/addons/crm_won_reason/wizard/__init__.py
odoo/addons/crm_won_reason/wizard/crm_lead_lost.py
odoo/addons/crm_won_reason/wizard/crm_lead_won.py
odoo/addons/crm_won_reason/wizard/crm_lead_won.xml
odoo_addon_crm_won_reason-15.0.1.0.0.10.dist-info/METADATA
odoo_addon_crm_won_reason-15.0.1.0.0.10.dist-info/WHEEL
odoo_addon_crm_won_reason-15.0.1.0.0.10.dist-info/top_level.txt
odoo_addon_crm_won_reason-15.0.1.0.0.10.dist-info/RECORD
